{
  "transcript_id": "93_3393767314028393843",
  "call_id": "3393767314028393843",
  "title": "Hiver Demo | Krys <> Yukta",
  "started": "2026-01-27T14:30:28+05:30",
  "signals": [
    {
      "Theme": "Customer Support",
      "Sub-Theme": "Centralized Solution",
      "Ask": "We need a customer support solution to centralize inquiries from multiple email accounts and social media.",
      "Priority": "High",
      "Evidence": "We are lacking in terms of the organization is some kind of like customer support solution where inquiries are coming in via different channels such as multiple email accounts… as well as social media."
    }
  ]
}